posit_cli/__init__.py
posit_cli/__main__.py
posit_cli/cli.py
posit_cli-0.1.1a1.dist-info/METADATA
posit_cli-0.1.1a1.dist-info/WHEEL
posit_cli-0.1.1a1.dist-info/entry_points.txt
posit_cli-0.1.1a1.dist-info/RECORD
