Metadata-Version: 2.1
Name: posit-cli
Version: 0.1.1a1
Summary: A command line tool for deploying and configuring Posit Workbench, Posit Connect, and Posit Posit Package Manager.
Home-page: https://github.com/sol-eng/posit-cli
Author: SamEdwardes
Author-email: sam.edwardes@posit.co
Requires-Python: >=3.9,<4.0
Classifier: Programming Language :: Python :: 3
Classifier: Programming Language :: Python :: 3.9
Classifier: Programming Language :: Python :: 3.10
Classifier: Programming Language :: Python :: 3.11
Requires-Dist: PyYAML (>=6.0,<7.0)
Requires-Dist: pulumi (>=3.46.1,<4.0.0)
Requires-Dist: pulumi-aws (>=5.20.0,<6.0.0)
Requires-Dist: pulumi-command (>=0.6.0,<0.7.0)
Requires-Dist: pydantic (>=1.10.2,<2.0.0)
Requires-Dist: rich (>=12.6.0,<13.0.0)
Requires-Dist: typer[all] (>=0.7.0,<0.8.0)
Project-URL: Documentation, https://github.com/sol-eng/posit-cli
Project-URL: Repository, https://github.com/sol-eng/posit-cli
